ds_stats/Binomial.py
ds_stats/BinomialDistribution.py
ds_stats/ChiSquareDistribution.py
ds_stats/ConfidenceInterval.py
ds_stats/FDistribution.py
ds_stats/NormalDistribution.py
ds_stats/PoissonDistribution.py
ds_stats/__init__.py
ds_stats/tDistribution.py
ds_stats-1.2.3.dist-info/DESCRIPTION.rst
ds_stats-1.2.3.dist-info/METADATA
ds_stats-1.2.3.dist-info/RECORD
ds_stats-1.2.3.dist-info/WHEEL
ds_stats-1.2.3.dist-info/metadata.json
ds_stats-1.2.3.dist-info/top_level.txt
