Metadata-Version: 2.0
Name: ds-stats
Version: 1.2.3
Summary: UNKNOWN
Home-page: UNKNOWN
Author: Sandeep
Author-email: mellacheruvu.sandeep@gmail.com
License: UNKNOWN
Platform: UNKNOWN
Requires-Dist: numpy
Requires-Dist: pandas
Requires-Dist: plotly
